devops_microsoft_client_real_time/__init__.py
devops_microsoft_client_real_time/factory/__init__.py
devops_microsoft_client_real_time/factory/factory.py
devops_microsoft_client_real_time/factory/service_enum.py
devops_microsoft_client_real_time/service/__init__.py
devops_microsoft_client_real_time/service/service.py
devops_microsoft_client_real_time-3.0.2.dist-info/METADATA
devops_microsoft_client_real_time-3.0.2.dist-info/WHEEL
devops_microsoft_client_real_time-3.0.2.dist-info/top_level.txt
devops_microsoft_client_real_time-3.0.2.dist-info/RECORD
