Metadata-Version: 2.1
Name: devops-microsoft-client-real-time
Version: 3.0.2
Summary: Responsible for sending commands to Seon DevOps microsoft Real Time job
Home-page: UNKNOWN
Author: Paulo Sergio dos Santo Junior
Author-email: paulossjuniort@gmail.com
License: UNKNOWN
Platform: UNKNOWN
Classifier: Programming Language :: Python :: 3
Classifier: License :: OSI Approved :: MIT License
Classifier: Operating System :: OS Independent
Requires-Dist: rabbitmqX
